wwtp/__init__.py
wwtp/py.typed
wwtp/api/__init__.py
wwtp/api/calculate.py
wwtp/api/flow_type.py
wwtp/api/settings.py
wwtp/api/toggleable.py
wwtp/api/units.py
wwtp/api/version.py
wwtp_api_rhdhv-0.6.0.dist-info/METADATA
wwtp_api_rhdhv-0.6.0.dist-info/WHEEL
wwtp_api_rhdhv-0.6.0.dist-info/top_level.txt
wwtp_api_rhdhv-0.6.0.dist-info/RECORD
