Metadata-Version: 2.1
Name: wwtp-api-rhdhv
Version: 0.6.0
Author: RoyalHaskoningDHV
Requires-Python: >=3.10
